eth_pm-0.1.0a23.dist-info/METADATA
eth_pm-0.1.0a23.dist-info/RECORD
eth_pm-0.1.0a23.dist-info/WHEEL
eth_pm-0.1.0a23.dist-info/top_level.txt
ethpm/__init__.py
ethpm/constants.py
ethpm/deployments.py
ethpm/exceptions.py
ethpm/package.py
ethpm/validation.py
ethpm/assets/Registry.sol
ethpm/assets/registry_abi.json
ethpm/typing/__init__.py
ethpm/typing/misc.py
ethpm/utils/__init__.py
ethpm/utils/chains.py
ethpm/utils/contract.py
ethpm/utils/deployment_validation.py
ethpm/utils/filesystem.py
ethpm/utils/ipfs.py
ethpm/utils/manifest_validation.py
ethpm/utils/registry.py
ethpm/utils/uri.py
