Metadata-Version: 2.1
Name: eth-pm
Version: 0.1.0a23
Summary: Python abstraction for ERC190 packages.
Home-page: https://github.com/ethpm/py-ethpm
Author: Piper Merriam
Author-email: pipermerriam@gmail.com
License: MIT
Keywords: ethereum
Platform: UNKNOWN
Classifier: Development Status :: 2 - Pre-Alpha
Classifier: Intended Audience :: Developers
Classifier: License :: OSI Approved :: MIT License
Classifier: Natural Language :: English
Classifier: Programming Language :: Python :: 3
Classifier: Programming Language :: Python :: 3.4
Classifier: Programming Language :: Python :: 3.5
Requires-Python: >=3.5, <4
Requires-Dist: toolz (<1.0.0,>=0.9.0)
Requires-Dist: cytoolz (<1.0.0,>=0.9.0)
Requires-Dist: bumpversion (<1,>=0.5.3)
Requires-Dist: eth-keys (<1,>=0.2.0b3)
Requires-Dist: eth-tester[py-evm] (==0.1.0-beta.26)
Requires-Dist: eth-utils (<2,>=1.0.2)
Requires-Dist: jsonschema (<3,>=2.6.0)
Requires-Dist: py-solc (<3,>=2.1.0)
Requires-Dist: rlp (<2,>=1.0.1)
Requires-Dist: web3 (<5,>=4.2.1)
Provides-Extra: dev
Requires-Dist: pytest-watch (<5,>=4.1.0); extra == 'dev'
Requires-Dist: pytest (<4,>=3.2.1); extra == 'dev'
Requires-Dist: tox (<2,>=1.8.0); extra == 'dev'
Requires-Dist: isort (<5,>=4.2.15); extra == 'dev'
Requires-Dist: flake8 (<4,>=3.5.0); extra == 'dev'
Requires-Dist: mypy (<0.600); extra == 'dev'
Requires-Dist: Sphinx (<2,>=1.5.5); extra == 'dev'
Requires-Dist: sphinx-rtd-theme (<2,>=0.1.9); extra == 'dev'
Provides-Extra: doc
Requires-Dist: Sphinx (<2,>=1.5.5); extra == 'doc'
Requires-Dist: sphinx-rtd-theme (<2,>=0.1.9); extra == 'doc'
Provides-Extra: lint
Requires-Dist: isort (<5,>=4.2.15); extra == 'lint'
Requires-Dist: flake8 (<4,>=3.5.0); extra == 'lint'
Requires-Dist: mypy (<0.600); extra == 'lint'
Provides-Extra: test
Requires-Dist: pytest (<4,>=3.2.1); extra == 'test'
Requires-Dist: tox (<2,>=1.8.0); extra == 'test'
